{"name":"Handyb","tagline":"Utility to manage android phone(s) via ADB over USB/WIFI","body":"# Handyb\r\n##\r\n### GUI for ADB (Android Debug Bridge)\r\n\r\nA simple, open-source, graphical Windows utility written in C# to carry out general ADB CLI operations with ease.\r\n\r\n![Screenshot](https://raw.githubusercontent.com/vaibhavpandeyvpz/handyb/master/Resources/screenshot.png \"Screenshot\")\r\n\r\nSince this is [on GitHub](https://github.com/vaibhavpandeyvpz/handyb), let me know if you forked and got some improvements ready to merge.\r\n\r\n### Credits:\r\n\r\n * [MadBee](https://github.com/camalot/madb) for Regexes\r\n * [Shota MIckaia](https://www.iconfinder.com/shotamickaia) for Icon\r\n","google":"UA-67528024-2","note":"Don't delete this file! It's used internally to help with page regeneration."}